bytedance_simple_rc_sampls_manage/__init__.py
bytedance_simple_rc_sampls_manage-0.0.1.dist-info/METADATA
bytedance_simple_rc_sampls_manage-0.0.1.dist-info/WHEEL
bytedance_simple_rc_sampls_manage-0.0.1.dist-info/top_level.txt
bytedance_simple_rc_sampls_manage-0.0.1.dist-info/RECORD
